test_html_parse_package/__init__.py
test_html_parse_package/html_parser.py
test_http_package/__init__.py
test_http_package/http_client.py
sankarsan_test_pkg-0.0.4.dist-info/METADATA
sankarsan_test_pkg-0.0.4.dist-info/WHEEL
sankarsan_test_pkg-0.0.4.dist-info/top_level.txt
sankarsan_test_pkg-0.0.4.dist-info/RECORD
