Metadata-Version: 2.4
Name: sankarsan-test-pkg
Version: 0.0.4
Summary: A simple test package
Author-email: Sankarsan Bose <sankarsan@gmail.com>
Classifier: Programming Language :: Python :: 3
Classifier: Operating System :: OS Independent
Requires-Python: >=3.8
Requires-Dist: requests
Requires-Dist: bs4
